nithinnnn/__init__.py
nithinnnn/hello.py
nithinnnn-0.1.0.dist-info/METADATA
nithinnnn-0.1.0.dist-info/WHEEL
nithinnnn-0.1.0.dist-info/top_level.txt
nithinnnn-0.1.0.dist-info/RECORD
